azure/mgmt/disconnectedoperations/__init__.py
azure/mgmt/disconnectedoperations/_client.py
azure/mgmt/disconnectedoperations/_configuration.py
azure/mgmt/disconnectedoperations/_patch.py
azure/mgmt/disconnectedoperations/_version.py
azure/mgmt/disconnectedoperations/py.typed
azure/mgmt/disconnectedoperations/_utils/__init__.py
azure/mgmt/disconnectedoperations/_utils/model_base.py
azure/mgmt/disconnectedoperations/_utils/serialization.py
azure/mgmt/disconnectedoperations/aio/__init__.py
azure/mgmt/disconnectedoperations/aio/_client.py
azure/mgmt/disconnectedoperations/aio/_configuration.py
azure/mgmt/disconnectedoperations/aio/_patch.py
azure/mgmt/disconnectedoperations/aio/operations/__init__.py
azure/mgmt/disconnectedoperations/aio/operations/_operations.py
azure/mgmt/disconnectedoperations/aio/operations/_patch.py
azure/mgmt/disconnectedoperations/models/__init__.py
azure/mgmt/disconnectedoperations/models/_enums.py
azure/mgmt/disconnectedoperations/models/_models.py
azure/mgmt/disconnectedoperations/models/_patch.py
azure/mgmt/disconnectedoperations/operations/__init__.py
azure/mgmt/disconnectedoperations/operations/_operations.py
azure/mgmt/disconnectedoperations/operations/_patch.py
azure_mgmt_disconnectedoperations-1.0.0b2.dist-info/licenses/LICENSE
azure_mgmt_disconnectedoperations-1.0.0b2.dist-info/METADATA
azure_mgmt_disconnectedoperations-1.0.0b2.dist-info/WHEEL
azure_mgmt_disconnectedoperations-1.0.0b2.dist-info/top_level.txt
azure_mgmt_disconnectedoperations-1.0.0b2.dist-info/RECORD
